kiwii/__init__.py
kiwii/architecture/__init__.py
kiwii/architecture/agent/__init__.py
kiwii/architecture/agent/parser/__init__.py
kiwii/architecture/agent/parser/consts.py
kiwii/architecture/agent/parser/parser.py
kiwii/architecture/client/__init__.py
kiwii/architecture/client/parser/__init__.py
kiwii/architecture/client/parser/consts.py
kiwii/architecture/client/parser/parser.py
kiwii/architecture/server/__init__.py
kiwii/architecture/server/parser/__init__.py
kiwii/architecture/server/parser/consts.py
kiwii/architecture/server/parser/parser.py
kiwii/kiwii.py
kiwii/parser/__init__.py
kiwii/parser/consts.py
kiwii/parser/parser.py
kiwii/shared/__init__.py
kiwii/shared/argparse_utils.py
kiwii/shared/models/__init__.py
kiwii/shared/models/argument.py
kiwii/shared/models/subparser.py
kiwii/shared/models/subparseraction.py
kiwii-0.1.0.dist-info/LICENSE
kiwii-0.1.0.dist-info/METADATA
kiwii-0.1.0.dist-info/WHEEL
kiwii-0.1.0.dist-info/entry_points.txt
kiwii-0.1.0.dist-info/RECORD
