Metadata-Version: 2.1
Name: kiwii
Version: 0.1.0
Summary: Home IOT ecosystem made easy.
License: Unlicense
Author: Vlad Poberezhny
Author-email: vlad.pbr@gmail.com
Requires-Python: >=3.11,<3.12
Classifier: License :: Other/Proprietary License
Classifier: Programming Language :: Python :: 3
Classifier: Programming Language :: Python :: 3.11
